two_m_root/__init__.py
two_m_root/conf.py
two_m_root/datatype.py
two_m_root/exceptions.py
two_m_root/orm.py
two_m_root/database/__init__.py
two_m_root/database/postgres/__init__.py
two_m_root/database/postgres/exceptions.py
two_m_root/dill/__init__.py
two_m_root/dill/serde.py
two_m_root/flasksqlalchemy/__init__.py
two_m_root/flasksqlalchemy/adapter.py
two_m_root/install/__init__.py
two_m_root/install/install.py
two_m_root/install/requirements.txt
two_m_root/templates/__init__.py
two_m_root/templates/main.py
two_m_root/templates/models.py
two_m_root/templates/procedures.py
two_m_root/templates/settings.env
2m-1.1.12.dist-info/METADATA
2m-1.1.12.dist-info/WHEEL
2m-1.1.12.dist-info/top_level.txt
2m-1.1.12.dist-info/RECORD
