Metadata-Version: 2.4
Name: 2m
Version: 1.1.12
Summary: A small package
Author-email: Victor Litovchenko <filpsixi@mail.ru>
Project-URL: Homepage, https://github.com/filthps/2m
Project-URL: Issues, https://github.com/filthps/2m/issues
Classifier: Programming Language :: Python :: 3
Classifier: Operating System :: OS Independent
Requires-Python: >=3.8
Requires-Dist: Flask==3.0.2
Requires-Dist: Flask-SQLAlchemy==3.1.1
Requires-Dist: importlib-metadata==8.6.1
Requires-Dist: pymemcache==4.0.0
Requires-Dist: python-dotenv==0.20.0
Requires-Dist: SQLAlchemy==2.0.28
Requires-Dist: SQLAlchemy-Utils==0.38.2
Requires-Dist: dill==0.3.9
Requires-Dist: psycopg2==2.9.3
